<?xml version="1.0"?>
<!DOCTYPE hibernate-mapping PUBLIC "-//Hibernate/Hibernate Mapping DTD 3.0//EN"
"http://hibernate.sourceforge.net/hibernate-mapping-3.0.dtd">
<!-- 
    Mapping file autogenerated by MyEclipse - Hibernate Tools
-->
<hibernate-mapping>
    <class name="com.yuntong.hibernate.database.po.TFilialeInfo" table="T_FilialeInfo" schema="dbo" catalog="BeltLine">
        <id name="filialeId" type="java.lang.Integer">
            <column name="FilialeID" />
            <generator class="assigned" />
        </id>
        <many-to-one name="TAreaInfo" class="com.yuntong.hibernate.database.po.TAreaInfo" fetch="select">
            <column name="FilialeAreaID" />
        </many-to-one>
        <property name="filialeName" type="java.lang.String">
            <column name="FilialeName" length="40" />
        </property>
        <property name="filialeLinkman" type="java.lang.String">
            <column name="FilialeLinkman" length="20" />
        </property>
        <property name="filialePhone" type="java.lang.String">
            <column name="FilialePhone" length="20" />
        </property>
        <property name="filialeAddress" type="java.lang.String">
            <column name="FilialeAddress" length="40" />
        </property>
        <property name="filialeEmail" type="java.lang.String">
            <column name="FilialeEmail" length="40" />
        </property>
        <set name="TTruckInfos" inverse="true">
            <key>
                <column name="TruckCompanyID" />
            </key>
            <one-to-many class="com.yuntong.hibernate.database.po.TTruckInfo" />
        </set>
        <set name="TUserInfos" inverse="true">
            <key>
                <column name="UserFilialeID" />
            </key>
            <one-to-many class="com.yuntong.hibernate.database.po.TUserInfo" />
        </set>
        <set name="TDriverInfos" inverse="true">
            <key>
                <column name="DriverCompanyID" />
            </key>
            <one-to-many class="com.yuntong.hibernate.database.po.TDriverInfo" />
        </set>
    </class>
</hibernate-mapping>
